tf_wrapper/__init__.py
tf_wrapper-1.0.0.dist-info/DESCRIPTION.rst
tf_wrapper-1.0.0.dist-info/METADATA
tf_wrapper-1.0.0.dist-info/RECORD
tf_wrapper-1.0.0.dist-info/WHEEL
tf_wrapper-1.0.0.dist-info/entry_points.txt
tf_wrapper-1.0.0.dist-info/metadata.json
tf_wrapper-1.0.0.dist-info/top_level.txt
