Metadata-Version: 2.0
Name: tf-wrapper
Version: 1.0.0
Summary: A terraform wrapper
Home-page: https://github.com/cpoole/tf-wrapper
Author: Matt Rabinovitch and Connor Poole
Author-email: connor.poole@daqri.com
License: MIT
Keywords: setuptools infrastructure terraform aws development
Platform: UNKNOWN
Classifier: Development Status :: 3 - Alpha
Classifier: Intended Audience :: Developers
Classifier: Topic :: Software Development :: Build Tools
Classifier: License :: OSI Approved :: MIT License
Classifier: Programming Language :: Python :: 2
Classifier: Programming Language :: Python :: 2.6
Classifier: Programming Language :: Python :: 2.7
Classifier: Programming Language :: Python :: 3
Classifier: Programming Language :: Python :: 3.3
Classifier: Programming Language :: Python :: 3.4
Classifier: Programming Language :: Python :: 3.5
Requires-Dist: tf-wrapper
Provides-Extra: dev
Requires-Dist: check-manifest; extra == 'dev'
Provides-Extra: test
Requires-Dist: coverage; extra == 'test'
